net_automation/__init__.py
net_automation/fsm.py
net_automation/net_automation.py
net_automation/requirements
net_automation/testing.py
net_automation/vyosbgp.template
net_automation_usman_u-0.0.28.dist-info/LICENSE
net_automation_usman_u-0.0.28.dist-info/METADATA
net_automation_usman_u-0.0.28.dist-info/WHEEL
net_automation_usman_u-0.0.28.dist-info/top_level.txt
net_automation_usman_u-0.0.28.dist-info/RECORD
