Metadata-Version: 2.1
Name: net-automation-usman-u
Version: 0.0.28
Summary: Network Automation
Home-page: https://github.com/usman-umer/network-automation
Author: Usman-U
Author-email: unumer@hotmail.com
Classifier: Programming Language :: Python :: 3
Classifier: License :: OSI Approved :: MIT License
Classifier: Operating System :: OS Independent
Requires-Python: >=3.6
License-File: LICENSE
